STARSA/__init__.py
STARSA/c9-D10.py
STARSA/phantoma.py
starsa-1.0.dist-info/licenses/LICENCE
starsa-1.0.dist-info/METADATA
starsa-1.0.dist-info/WHEEL
starsa-1.0.dist-info/top_level.txt
starsa-1.0.dist-info/RECORD
