Metadata-Version: 2.4
Name: STARSA
Version: 1.0
License-File: LICENCE
Dynamic: description
Dynamic: license-file
